WEEK5/1/exec.v
module exec(in1, in2, result);
    input in1,in2;
    output result;
    wire in1,in2,out1,outA,outB,result;
    
    //객체 만들어줘야함
    AND a1(in1,in2,outA); // in1 & in2
    
    NOT a2(in2,out1);
    AND a3(in1,out1,outB); // in1 & ~in2

    OR a4(outA,outB,result); // out1 | outB
endmodule

WEEK7/modules.v
module XOR(in1, in2, out);
    input in1,in2;
    output out;
    wire in1,in2,out;
    assign out = in1 ^ in2;
endmodule

module AND(in1, in2, out);
    input in1,in2;
    output out;
    wire in1,in2,out;
    assign out = in1 & in2;
endmodule

module OR(in1, in2, out);
    input in1,in2;
    output out;
    wire in1,in2,out;
    assign out = in1 | in2;
endmodule

WEEK7/halfadder.v
module HalfAdder(in1, in2, S, C);

    input in1,in2;
    output S,C;
    wire in1,in2,S,C;

    XOR a(in1,in2,S);
    AND b(in1,in2,C);
    
endmodule

WEEK6/bench.v
`timescale 1ns/1ns
`include "modules.v"
`include "exec.v"
module bench;

reg inA,inB,Cin; // 초기 input 으로 들어가는 register
wire C1,C2,S; // module output 을 묶어주기 위해 wire 선언
wire Cout,Sum; // result output

HalfAdder aa(.in1(inA), .in2(inB), .S(S), .C(C1));
HalfAdder bb(.in1(S), .in2(Cin), .S(Sum), .C(C2)); // Sum
OR cc(.in1(C1), .in2(C2), .out(Cout)); // Cout 

initial begin
    $dumpfile("test2.vcd");
    $dumpvars(1);
end

initial begin
    #10 inA=0;inB=0;Cin=0;
    #10 inA=0;inB=0;Cin=1;
    #10 inA=0;inB=1;Cin=0;
    #10 inA=0;inB=1;Cin=1;
    #10 inA=1;inB=0;Cin=0;
    #10 inA=1;inB=0;Cin=1;
    #10 inA=1;inB=1;Cin=0;
    #10 inA=1;inB=1;Cin=1;
    #10 $finish;
end

endmodule

WEEK6/test.vcd
$date
	Tue Apr 06 16:41:10 2021
$end
$version
	Icarus Verilog
$end
$timescale
	1ns
$end
$scope module bench $end
$var wire 1 ! Sum $end
$var wire 1 " S $end
$var wire 1 # Cout $end
$var wire 1 $ C2 $end
$var wire 1 % C1 $end
$var reg 1 & Cin $end
$var reg 1 ' inA $end
$var reg 1 ( inB $end
$upscope $end
$enddefinitions $end
#0
$dumpvars
x(
x'
x&
x%
x$
x#
x"
x!
$end
#10
0#
0!
0$
0"
0%
0&
0(
0'
#20
1!
1&
#30
1"
0&
1(
#40
1#
0!
1$
1&
#50
0#
1!
0$
0&
0(
1'
#60
1#
0!
1$
1&
#70
0$
0"
1%
0&
1(
#80
1!
1&
