WEEK13/blk_nblk.v
module BLK_NBLK(BLK_in1, NBLK_in1, clk, 
                BLK_out1, BLK_out2, NBLK_out1, NBLK_out2);
    input[3:0] BLK_in1, NBLK_in1;
    input clk;
    output[3:0] BLK_out1, BLK_out2, NBLK_out1, NBLK_out2;
    reg[3:0] BLK_out1, BLK_out2, NBLK_out1, NBLK_out2;
    wire clk;

    //BLK
    always@(posedge clk)
    begin
        BLK_out1 = BLK_in1;
        BLK_out2 = BLK_out1;
    end

    //NBLK
    always@(negedge clk)
    begin
        NBLK_out1 <= NBLK_in1;
        NBLK_out2 <= NBLK_out1;
    end

endmodule

module D_LATCH_FF(D, clk, Latch_out, FF_out);
    input[3:0] D; 
    input clk;
    output[3:0] Latch_out, FF_out;
    reg[3:0] Latch_out, FF_out;
    wire clk;

    always@(posedge clk)
    begin
        Latch_out = D;
    end

    always @(negedge clk or posedge clk) 
    begin
        FF_out <= D;
    end

endmodule

WEEK13/tb.v
`timescale 1ns/1ns
`include "blk_nblk.v"
module tb;
    reg[3:0] BLK_in1, NBLK_in1;
    reg[3:0] D;
    reg clk;
    wire[3:0] BLK_out1, BLK_out2, NBLK_out1, NBLK_out2;
    wire[3:0] Latch_out, FF_out;

    BLK_NBLK a(BLK_in1, NBLK_in1, clk,
                BLK_out1, BLK_out2, NBLK_out1, NBLK_out2);
    D_LATCH_FF aa(D, clk, Latch_out, FF_out);
    initial begin
        $dumpfile("test.vcd");
        $dumpvars(1);
    end

    always begin
        #5 clk=~clk;
    end

    initial begin
        clk = 1'b0;
        #10 BLK_in1 = 4'b0001; NBLK_in1=4'b0001; D=4'b0001;
        #10 BLK_in1 = 4'b0010; NBLK_in1=4'b0010; D=4'b0010;
        #10 BLK_in1 = 4'b0011; NBLK_in1=4'b0011; D=4'b0011;
        #10 BLK_in1 = 4'b0100; NBLK_in1=4'b0100; D=4'b0100;
        #10 BLK_in1 = 4'b0101; NBLK_in1=4'b0101; D=4'b0101;
        #10 BLK_in1 = 4'b0110; NBLK_in1=4'b0110; D=4'b0110;
        #10 $finish;
    end

endmodule

WEEK13/test.vcd
$date
	Tue May 25 17:13:57 2021
$end
$version
	Icarus Verilog
$end
$timescale
	1ns
$end
$scope module tb $end
$var wire 4 ! NBLK_out2 [3:0] $end
$var wire 4 " NBLK_out1 [3:0] $end
$var wire 4 # Latch_out [3:0] $end
$var wire 4 $ FF_out [3:0] $end
$var wire 4 % BLK_out2 [3:0] $end
$var wire 4 & BLK_out1 [3:0] $end
$var reg 4 ' BLK_in1 [3:0] $end
$var reg 4 ( D [3:0] $end
$var reg 4 ) NBLK_in1 [3:0] $end
$var reg 1 * clk $end
$upscope $end
$enddefinitions $end
#0
$dumpvars
0*
bx )
bx (
bx '
bx &
bx %
bx $
bx #
bx "
bx !
$end
#5
1*
#10
b1 "
b1 $
0*
b1 (
b1 )
b1 '
#15
b1 #
b1 %
b1 &
1*
#20
b1 !
b10 "
b10 $
0*
b10 (
b10 )
b10 '
#25
b10 %
b10 &
b10 #
1*
#30
b10 !
b11 "
b11 $
0*
b11 (
b11 )
b11 '
#35
b11 #
b11 %
b11 &
1*
#40
b11 !
b100 "
b100 $
0*
b100 (
b100 )
b100 '
#45
b100 %
b100 &
b100 #
1*
#50
b100 !
b101 "
b101 $
0*
b101 (
b101 )
b101 '
#55
b101 #
b101 %
b101 &
1*
#60
b101 !
b110 "
b110 $
0*
b110 (
b110 )
b110 '
#65
b110 %
b110 &
b110 #
1*
#70
b110 !
0*
