WEEK4/ex03.v
module ex03(inX,inY,out);

    input inX,inY;
    output out;
    wire inX,inY;
    wire out;
    assign out = inX & inY;

endmodule

WEEK2/ex02.v
module ex02(in1, in2, in3, out1);

    input in1,in2,in3;
    output out1;

    wire in1,in2,in3;
    wire out1;

    assign out1=in1&in2&in3;
endmodule

WEEK1/ex01.v
module ex01(in1, in2, out1);
	// Port 선언부 //    
	input in1, in2;  
	output out1;    
	wire in1, in2;  
	wire out1;	
	// 연산부 //   
	assign out1 = in1 & in2;
	// assign 은 값을 저장하는게 아니라 전달하는 것
	// assign 할때는 wire를 사용한다
endmodule

WEEK4/ex02_tb.v
`timescale 100ns/10ns
`include "ex02.v"
`include "ex01.v"
`include "ex03.v"
module ex03_tb; //파일명과 무관
reg in1,in2,in3;
wire outA, outB, outC;
ex01 a(.in1(in1), .in2(in2), .out1(outA));
ex02 b(.in1(in1), .in2(in2), .in3(in3), .out1(outB));
ex03 c(.inX(in1), .inY(in2), .out(outC));
initial begin
    $dumpfile("ex02_out.vcd");
    $dumpvars(1);
end

initial begin
    #10 in1 = 0; in2 = 0; in3 = 0;
    #10 in1 = 0; in2 = 0; in3 = 1;
    #10 in1 = 0; in2 = 1; in3 = 0;
    #10 in1 = 0; in2 = 1; in3 = 1;
    #10 in1 = 1; in2 = 0; in3 = 0;
    #10 in1 = 1; in2 = 0; in3 = 1;
    #10 in1 = 1; in2 = 1; in3 = 0;
    #10 in1 = 1; in2 = 1; in3 = 1;
    #10 $finish;
end
endmodule

WEEK4/ex02_out.vcd
$date
	Tue Mar 30 16:01:09 2021
$end
$version
	Icarus Verilog
$end
$timescale
	10ns
$end
$scope module ex03_tb $end
$var wire 1 ! outC $end
$var wire 1 " outB $end
$var wire 1 # outA $end
$var reg 1 $ in1 $end
$var reg 1 % in2 $end
$var reg 1 & in3 $end
$upscope $end
$enddefinitions $end
#0
$dumpvars
x&
x%
x$
x#
x"
x!
$end
#100
0"
0#
0!
0&
0%
0$
#200
1&
#300
0&
1%
#400
1&
#500
0&
0%
1$
#600
1&
#700
1#
1!
0&
1%
#800
1"
1&
