final/FSM.v
module FSM(state, Data_in, nRESET, CLK);
 
    input[1:0] Data_in;
    input nRESET, CLK;
    output[3:0] state;
    
    wire[1:0] Data_in; // 0: straight, 1: left, 2: right, 3: stop
    wire nRESET, CLK;
    reg[3:0] state; // A,B,C,D

    parameter[1:0] A=2'h0, B=2'h1, C=2'h2, D=2'h3;

    always @(CLK) begin
        if(nRESET == 1'b1) state=A;
        else begin
            case(state)
                A: begin
                    if(Data_in == 2'b00) state = D;
                    else if(Data_in==2'b01) state = B;
                    else if(Data_in==2'b10) state = C;
                    else state=A;
                end
                B: begin
                    if(Data_in == 2'b00) state = C;
                    else if(Data_in==2'b01) state = D;
                    else if(Data_in==2'b10) state = A;
                    else state=B;
                end
                C: begin
                    if(Data_in == 2'b00) state = B;
                    else if(Data_in==2'b01) state = A;
                    else if(Data_in==2'b10) state = D;
                    else state=C;
                end
                D: begin
                    if(Data_in == 2'b00) state = A;
                    else if(Data_in==2'b01) state = C;
                    else if(Data_in==2'b10) state = B;
                    else state=D;
                end
            endcase
        end
    end
     
 endmodule

final/FSM_TEST.v
`timescale 1ns/1ns
`include "FSM.v"

module FSM_TEST;

    reg[1:0] Data_in;
    reg CLK, nRESET;

    wire[3:0] state;

    // wire[3:0] nextState;
    
    FSM a(.state(state), .Data_in(Data_in), .nRESET(nRESET), .CLK(CLK));

    initial begin
        $dumpfile("test.vcd");
        $dumpvars(1);
    end

    always begin
        #10 CLK = ~CLK;
    end

    initial begin
        nRESET = 1'b1; CLK = 1'b0;
        #10 nRESET = 1'b0;
        #10 Data_in = 2'b11; 
        #10 Data_in = 2'b01; 
        #10 Data_in = 2'b01;
        #10 Data_in = 2'b00;
        #10 Data_in = 2'b01;
        #10 Data_in = 2'b10; 
        #10 Data_in = 2'b00; 
        #10 Data_in = 2'b10;
        #10 Data_in = 2'b10;
        #10 Data_in = 2'b00; 
        #10 $finish;
    end

endmodule

final/test.vcd
$date
	Thu Dec 09 23:17:13 2021
$end
$version
	Icarus Verilog
$end
$timescale
	1ns
$end
$scope module FSM_TEST $end
$var wire 4 ! state [3:0] $end
$var reg 1 " CLK $end
$var reg 2 # Data_in [1:0] $end
$var reg 1 $ nRESET $end
$upscope $end
$enddefinitions $end
#0
$dumpvars
1$
bx #
0"
b0 !
$end
#10
0$
1"
#20
b11 #
0"
#30
b1 !
b1 #
1"
#40
b11 !
0"
#50
b0 !
b0 #
1"
#60
b1 !
b1 #
0"
#70
b0 !
b10 #
1"
#80
b11 !
b0 #
0"
#90
b1 !
b10 #
1"
#100
b0 !
0"
#110
b11 !
b0 #
1"
#120
b0 !
0"
